Metadata-Version: 2.4
Name: trinix
Version: 0.1.3
Summary: High-performance PyTorch layers with optimized Triton kernels and Flash Attention support
Author-email: Gitesh Chawda <gitesh.ch.0912@gmail.com>
License-Expression: Apache-2.0
Project-URL: documentation, https://github.com/IMvision12/trinix
Project-URL: repository, https://github.com/IMvision12/trinix
Keywords: triton,flash attention,pytorch,llm,machine learning,deep learning
Classifier: Development Status :: 3 - Alpha
Classifier: Intended Audience :: Developers
Classifier: Programming Language :: Python :: 3
Classifier: Programming Language :: Python :: 3.8
Classifier: Programming Language :: Python :: 3.9
Classifier: Programming Language :: Python :: 3.10
Classifier: Programming Language :: Python :: 3.11
Requires-Python: <3.14,>=3.9
License-File: LICENSE
Requires-Dist: torch>=2.0.0
Requires-Dist: numpy>=1.20.0
Provides-Extra: gpu
Requires-Dist: triton>=2.0.0; extra == "gpu"
Requires-Dist: flash-attn>=2.0.0; extra == "gpu"
Provides-Extra: tests
Requires-Dist: pytest>=7.0.0; extra == "tests"
Requires-Dist: pytest-cov>=4.0.0; extra == "tests"
Provides-Extra: all
Requires-Dist: triton>=2.0.0; extra == "all"
Requires-Dist: flash-attn>=2.0.0; extra == "all"
Requires-Dist: pytest>=7.0.0; extra == "all"
Requires-Dist: pytest-cov>=4.0.0; extra == "all"
Dynamic: license-file
